recommender_ibmws/__init__.py
recommender_ibmws/recommender.py
recommender_ibmws/recommender_functions.py
recommender_ibmws/data/articles_community.csv
recommender_ibmws/data/user-item-interactions.csv
recommender_ibmws-0.1.3.dist-info/LICENSE
recommender_ibmws-0.1.3.dist-info/METADATA
recommender_ibmws-0.1.3.dist-info/WHEEL
recommender_ibmws-0.1.3.dist-info/top_level.txt
recommender_ibmws-0.1.3.dist-info/RECORD
