Metadata-Version: 2.1
Name: recommender_ibmws
Version: 0.1.3
Summary: User article recommender system for IBM Watson Studio
Home-page: https://github.com/joanamdsantos/recommender_ibmws_pkg
Author: Joana Martins dos Santos
Author-email: Joana Martins dos Santos <joanamlmsantos@gmail.com>
Project-URL: Homepage, https://github.com/joanamdsantos/recommender_ibmws_pkg
Project-URL: Issues, https://github.com/joanamdsantos/recommender_ibmws_pkg/issues
Classifier: Programming Language :: Python :: 3
Classifier: License :: OSI Approved :: MIT License
Classifier: Operating System :: OS Independent
Requires-Python: >=3.12
License-File: LICENSE
